[
  {
    "CdsFCBContext": "{\"FileType\":true,\"ImageExternalStorage\":true}",
    "EntitySetName": "crfb9_activo_ops",
    "IsHidden": false,
    "IsSampleData": false,
    "IsWritable": true,
    "LogicalName": "crfb9_activo_op",
    "MaxGetRowsCount": 500,
    "Name": "Activo_Ops",
    "NativeCDSDataSourceInfoNameMapping": {
      "_ownerid_value": "Propietario",
      "createdby": "Autor",
      "createdon": "Fecha de creación",
      "createdonbehalfby": "Autor (delegado)",
      "crfb9_activo": "Activo",
      "crfb9_activo_op_AsyncOperations": "Trabajos del sistema",
      "crfb9_activo_op_BulkDeleteFailures": "Errores de eliminación en masa",
      "crfb9_activo_op_MailboxTrackingFolders": "Carpetas de seguimiento automático del buzón",
      "crfb9_activo_op_PrincipalObjectAttributeAccesses": "Uso compartido de campos",
      "crfb9_activo_op_ProcessSession": "Sesiones de proceso",
      "crfb9_activo_op_SyncErrors": "Errores de sincronización",
      "crfb9_activo_opid": "Activo_Op",
      "crfb9_id_activo": "Id_Activo",
      "importsequencenumber": "Número de secuencia de importación",
      "modifiedby": "Modificado por",
      "modifiedon": "Fecha de modificación",
      "modifiedonbehalfby": "Modificado por (delegado)",
      "overriddencreatedon": "Fecha de creación del registro",
      "owningbusinessunit": "Unidad de negocio propietaria",
      "owningteam": "Equipo propietario",
      "owninguser": "Usuario propietario",
      "statecode": "Estado",
      "statuscode": "Razón para el estado",
      "timezoneruleversionnumber": "Número de versión de regla de zona horaria",
      "utcconversiontimezonecode": "Código de zona horaria de conversión UTC",
      "versionnumber": "Número de versión"
    },
    "PreferredName": "Activo_Ops",
    "Type": "NativeCDSDataSourceInfo"
  },
  {
    "DisplayName": "Activo_Ops (Views)",
    "Name": "_crfb9_activo_op_views",
    "RelatedEntityName": "Activo_Ops",
    "TrimmedViewName": true,
    "Type": "ViewInfo",
    "ViewInfoNameMapping": {
      "404d9b0e-9ce6-417c-bbce-ebf8031c6c54": "Vista de búsqueda avanzada de Activo_Op",
      "498deec3-040c-400b-b4f4-7b2494724c53": "Activo_Ops inactivo",
      "8def54be-b8d3-4ca3-81e0-559e3f90ba97": "Activo_Ops activo",
      "be9824ac-3bde-4b3c-850b-b914da892120": "Vista de búsqueda de Activo_Op",
      "cb23caca-dfc1-462f-87be-41dd4a5b8773": "Vista asociada de Activo_Op"
    }
  },
  {
    "DisplayName": "Activo (Activo_Ops)",
    "Name": "crfb9_activo_op_crfb9_activo",
    "OptionSetInfoNameMapping": {
      "0": "No",
      "1": "Si"
    },
    "OptionSetIsBooleanValued": true,
    "OptionSetIsGlobal": false,
    "OptionSetReference": {
      "OptionSetReferenceItem0": {
        "OptionSetReferenceColumnName": "crfb9_activo",
        "OptionSetReferenceEntityName": "Activo_Ops"
      }
    },
    "OptionSetTypeKey": "BooleanType",
    "RelatedColumnInvariantName": "crfb9_activo",
    "RelatedEntityName": "Activo_Ops",
    "Type": "OptionSetInfo"
  },
  {
    "DisplayName": "Estado (Activo_Ops)",
    "Name": "crfb9_activo_op_statecode",
    "OptionSetInfoNameMapping": {
      "0": "Activo",
      "1": "Inactivo"
    },
    "OptionSetIsBooleanValued": false,
    "OptionSetIsGlobal": false,
    "OptionSetReference": {
      "OptionSetReferenceItem0": {
        "OptionSetReferenceColumnName": "statecode",
        "OptionSetReferenceEntityName": "Activo_Ops"
      }
    },
    "OptionSetTypeKey": "StateType",
    "RelatedColumnInvariantName": "statecode",
    "RelatedEntityName": "Activo_Ops",
    "Type": "OptionSetInfo"
  },
  {
    "DisplayName": "Razón para el estado (Activo_Ops)",
    "Name": "crfb9_activo_op_statuscode",
    "OptionSetInfoNameMapping": {
      "1": "Activo",
      "2": "Inactivo"
    },
    "OptionSetIsBooleanValued": false,
    "OptionSetIsGlobal": false,
    "OptionSetReference": {
      "OptionSetReferenceItem0": {
        "OptionSetReferenceColumnName": "statuscode",
        "OptionSetReferenceEntityName": "Activo_Ops"
      }
    },
    "OptionSetTypeKey": "StatusType",
    "RelatedColumnInvariantName": "statuscode",
    "RelatedEntityName": "Activo_Ops",
    "Type": "OptionSetInfo"
  }
]